caistro/__init__.py
caistro/client.py
caistro/types.py
caistro-0.1.0.dist-info/METADATA
caistro-0.1.0.dist-info/WHEEL
caistro-0.1.0.dist-info/RECORD
